pub_utils_hhb/__init__.py
pub_utils_hhb/pub_args_util.py
pub_utils_hhb/pub_common_util.py
pub_utils_hhb/pub_config_util.py
pub_utils_hhb/pub_crypt_util.py
pub_utils_hhb/pub_logger_util.py
pub_utils_hhb/pub_time_util.py
pub_utils_hhb-0.0.4.dist-info/METADATA
pub_utils_hhb-0.0.4.dist-info/WHEEL
pub_utils_hhb-0.0.4.dist-info/entry_points.txt
pub_utils_hhb-0.0.4.dist-info/top_level.txt
pub_utils_hhb-0.0.4.dist-info/RECORD
